pcaspy_utils/__init__.py
pcaspy_utils/shell_commands.py
pcaspy_utils-0.0.3.dist-info/METADATA
pcaspy_utils-0.0.3.dist-info/WHEEL
pcaspy_utils-0.0.3.dist-info/top_level.txt
pcaspy_utils-0.0.3.dist-info/RECORD
